bootstrap.py
buildout.cfg
setup.py
docs/CREDITS.TXT
docs/LICENSE.GPL
docs/LICENSE.txt
docs/README.txt
docs/protocol.txt
src/kss/__init__.py
src/kss.base.egg-info/PKG-INFO
src/kss.base.egg-info/SOURCES.txt
src/kss.base.egg-info/dependency_links.txt
src/kss.base.egg-info/entry_points.txt
src/kss.base.egg-info/not-zip-safe
src/kss.base.egg-info/requires.txt
src/kss.base.egg-info/top_level.txt
src/kss/base/EXTERNALS.txt
src/kss/base/__init__.py
src/kss/base/commands.py
src/kss/base/commands.txt
src/kss/base/commandset.py
src/kss/base/config-sample.in
src/kss/base/config.py
src/kss/base/corecommands.py
src/kss/base/corecommands.txt
src/kss/base/javascript.py
src/kss/base/javascript.txt
src/kss/base/plugin.py
src/kss/base/plugin.txt
src/kss/base/registry.py
src/kss/base/registry.txt
src/kss/base/selectors.py
src/kss/base/selectors.txt
src/kss/base/tests.py
src/kss/base/utils.py
src/kss/base/compression/__init__.py
src/kss/base/compression/css.py
src/kss/base/compression/javascript.py
src/kss/base/compression/thirdparty/LICENSE
src/kss/base/compression/thirdparty/__init__.py
src/kss/base/compression/thirdparty/packer.py
src/kss/base/kukit/tests.bat
src/kss/base/kukit/version.txt
src/kss/base/kukit/3rd_party/LICENSE.txt
src/kss/base/kukit/3rd_party/MochiKit.js
src/kss/base/kukit/3rd_party/base2-dom-fp.js
src/kss/base/kukit/3rd_party/cssQuery-compat.js
src/kss/base/kukit/3rd_party/cssQuery.js
src/kss/base/kukit/3rd_party/sarissa.js
src/kss/base/kukit/3rd_party/firebuglite/errorIcon.png
src/kss/base/kukit/3rd_party/firebuglite/firebug.css
src/kss/base/kukit/3rd_party/firebuglite/firebug.html
src/kss/base/kukit/3rd_party/firebuglite/firebug.js
src/kss/base/kukit/3rd_party/firebuglite/firebugx.js
src/kss/base/kukit/3rd_party/firebuglite/infoIcon.png
src/kss/base/kukit/3rd_party/firebuglite/warningIcon.png
src/kss/base/kukit/3rd_party/johnnydebris.net/dommer/CHANGES.txt
src/kss/base/kukit/3rd_party/johnnydebris.net/dommer/LICENSE.txt
src/kss/base/kukit/3rd_party/johnnydebris.net/dommer/README.txt
src/kss/base/kukit/3rd_party/johnnydebris.net/dommer/conftest.py
src/kss/base/kukit/3rd_party/johnnydebris.net/dommer/dommer.js
src/kss/base/kukit/3rd_party/johnnydebris.net/dommer/example.html
