Metadata-Version: 1.0
Name: kss.base
Version: 0.3
Summary: KSS (Kinetic Style Sheets) framework
Home-page: http://kssproject.org
Author: KSS Project
Author-email: kss-devel@codespeak.net
License: GPL
Platform: UNKNOWN
Classifier: Development Status :: 3 - Alpha
Classifier: Framework :: Paste
Classifier: Intended Audience :: Developers
Classifier: License :: OSI Approved :: GNU General Public License (GPL)
Classifier: Operating System :: OS Independent
Classifier: Programming Language :: Python
Classifier: Programming Language :: JavaScript
Classifier: Topic :: Software Development :: Libraries :: Python Modules
